buster/__init__.py
buster/busterbot.py
buster/completers/__init__.py
buster/completers/base.py
buster/completers/chatgpt.py
buster/completers/user_inputs.py
buster/documents_manager/__init__.py
buster/documents_manager/base.py
buster/documents_manager/deeplake.py
buster/documents_manager/service.py
buster/examples/cfg.py
buster/examples/deeplake_store.zip
buster/examples/generate_embeddings.py
buster/examples/gradio_app.py
buster/examples/stackoverflow.csv
buster/formatters/documents.py
buster/formatters/prompts.py
buster/imgs/qa_web_load.png
buster/imgs/qa_web_oom.png
buster/llm_utils/__init__.py
buster/llm_utils/embeddings.py
buster/llm_utils/question_reformulator.py
buster/notebooks/db_to_csv.ipynb
buster/parsers/__init__.py
buster/parsers/parser.py
buster/retriever/__init__.py
buster/retriever/base.py
buster/retriever/deeplake.py
buster/retriever/service.py
buster/tokenizers/__init__.py
buster/tokenizers/base.py
buster/tokenizers/gpt.py
buster/utils.py
buster/validators/__init__.py
buster/validators/base.py
buster/validators/validators.py
buster_doctalk-1.0.28.dist-info/LICENSE.md
buster_doctalk-1.0.28.dist-info/METADATA
buster_doctalk-1.0.28.dist-info/WHEEL
buster_doctalk-1.0.28.dist-info/RECORD
