Metadata-Version: 2.1
Name: buster-doctalk
Version: 1.0.28
Summary: Buster 🤖: A chatbot for retrieval-augmented generation
Home-page: https://github.com/jerpint/buster
License: MIT
Author: Jeremy Pinto
Author-email: jerpint@gmail.com
Requires-Python: >=3.10,<3.13
Classifier: License :: OSI Approved :: MIT License
Classifier: Programming Language :: Python :: 3
Classifier: Programming Language :: Python :: 3.10
Classifier: Programming Language :: Python :: 3.11
Classifier: Programming Language :: Python :: 3.12
Requires-Dist: bs4 (>=0.0.2,<0.0.3)
Requires-Dist: click (>=8.1.7,<9.0.0)
Requires-Dist: deeplake (>=3.8.19,<4.0.0)
Requires-Dist: gradio (>=3.40)
Requires-Dist: matplotlib (>=3.8.2,<4.0.0)
Requires-Dist: numpy (>=1.25)
Requires-Dist: openai (>=1.0)
Requires-Dist: pandas (>=2.1.3)
Requires-Dist: pinecone-client (>=3.0.2)
Requires-Dist: pinecone-text (>=0.6.0)
Requires-Dist: pymongo (>=4.6.1,<5.0.0)
Requires-Dist: pytest (>=8.0.0,<9.0.0)
Requires-Dist: tabulate (>=0.9.0,<0.10.0)
Requires-Dist: tenacity (>=8.2.3,<9.0.0)
Requires-Dist: tiktoken (>=0.5.2,<0.6.0)
Project-URL: Repository, https://github.com/jerpint/buster
